Metadata-Version: 2.1
Name: element-manager
Version: 1.0.3
Summary: Selenium Element Finder Library
Home-page: UNKNOWN
Author: DataKund
Author-email: datakund@gmail.com
License: Apache License 2.0
Keywords: selenium no-html web-scraping bots test-automation no-code low-code cloud proxy datakund
Platform: UNKNOWN
